{
  "id": "radar_detector",
  "title": "Radar Palindrome Detector",
  "description": "Input: `s` (str) signal. Return: `True` if signal is palindrome (reads same forwards and backwards), else `False`.",
  "difficulty": "Easy",
  "tags": [
    "strings",
    "logic"
  ],
  "hints": [
    "Check if string equals its reverse"
  ],
  "function_signature": "def solve(s):\n    \"\"\"\n    Return result, do not print\n    \"\"\"\n    pass",
  "sample_input": "'madam'",
  "sample_output": "True",
  "test_cases": [
    {
      "input": "'madam'",
      "output": "True"
    },
    {
      "input": "'python'",
      "output": "False"
    },
    {
      "input": "'level'",
      "output": "True"
    },
    {
      "input": "'a'",
      "output": "True"
    },
    {
      "input": "'ab'",
      "output": "False"
    }
  ]
}